flask_restapi/__init__.py
flask_restapi/commands.py
flask_restapi/core.py
flask_restapi/exceptions.py
flask_restapi/mixins.py
flask_restapi/spec/__init__.py
flask_restapi/spec/core.py
flask_restapi/spec/models.py
flask_restapi/templates/swagger_ui.html
flask_restapi/tool/__init__.py
flask_restapi/tool/core.py
flask_restapi/tool/template.py
flask_restapi/types.py
flask_restapi-0.3.1.dist-info/LICENSE
flask_restapi-0.3.1.dist-info/WHEEL
flask_restapi-0.3.1.dist-info/METADATA
flask_restapi-0.3.1.dist-info/RECORD
