Metadata-Version: 2.1
Name: flask-restapi
Version: 0.3.1
Summary: Flask-RESTAPI is an extension for validate and make OpenAPI docs.
Home-page: https://github.com/JonarsLi/flask-restapi
License: MIT
Author: jonars
Author-email: jonarsli13@gmail.com
Requires-Python: >=3.7,<4.0
Classifier: License :: OSI Approved :: MIT License
Classifier: Programming Language :: Python :: 3
Classifier: Programming Language :: Python :: 3.10
Classifier: Programming Language :: Python :: 3.7
Classifier: Programming Language :: Python :: 3.8
Classifier: Programming Language :: Python :: 3.9
Requires-Dist: Flask[async] (>=2.0.1,<3.0.0)
Requires-Dist: PyJWT (>=2.3.0,<3.0.0)
Requires-Dist: pydantic (>=1.8.2,<2.0.0)
Project-URL: Documentation, https://jonarsli.github.io/flask-restapi/
Project-URL: Repository, https://github.com/JonarsLi/flask-restapi
